bleak_esphome/__init__.py
bleak_esphome/connect.py
bleak_esphome/connection_manager.py
bleak_esphome/py.typed
bleak_esphome/backend/__init__.py
bleak_esphome/backend/cache.py
bleak_esphome/backend/client.py
bleak_esphome/backend/device.py
bleak_esphome/backend/scanner.cpython-313-x86_64-linux-musl.so
bleak_esphome/backend/scanner.pxd
bleak_esphome/backend/scanner.py
bleak_esphome-3.3.0.dist-info/LICENSE
bleak_esphome-3.3.0.dist-info/METADATA
bleak_esphome-3.3.0.dist-info/WHEEL
bleak_esphome-3.3.0.dist-info/RECORD
