Metadata-Version: 2.3
Name: bleak-esphome
Version: 3.3.0
Summary: Bleak backend of ESPHome
License: MIT
Author: J. Nick Koston
Author-email: bluetooth@koston.org
Requires-Python: >=3.11
Classifier: Development Status :: 2 - Pre-Alpha
Classifier: Intended Audience :: Developers
Classifier: License :: OSI Approved :: MIT License
Classifier: Natural Language :: English
Classifier: Operating System :: OS Independent
Classifier: Programming Language :: Python :: 3
Classifier: Programming Language :: Python :: 3.11
Classifier: Programming Language :: Python :: 3.12
Classifier: Programming Language :: Python :: 3.13
Classifier: Topic :: Software Development :: Libraries
Requires-Dist: aioesphomeapi (>=30.1.0)
Requires-Dist: bleak (>=1)
Requires-Dist: bleak-retry-connector (>=3.8.0)
Requires-Dist: bluetooth-data-tools (>=1.18.0)
Requires-Dist: habluetooth (>=5.4.0)
Requires-Dist: lru-dict (>=1.2.0)
Project-URL: Bug Tracker, https://github.com/bluetooth-devices/bleak-esphome/issues
Project-URL: Changelog, https://github.com/bluetooth-devices/bleak-esphome/blob/main/CHANGELOG.md
Project-URL: Documentation, https://bleak-esphome.readthedocs.io
Project-URL: Repository, https://github.com/bluetooth-devices/bleak-esphome
